delpinos/crud/sqlalchemy/config.py
delpinos/crud/sqlalchemy/connection.py
delpinos/crud/sqlalchemy/application/encoders/sqlalchemy_encoder.py
delpinos/crud/sqlalchemy/application/models/sqlalchemy_model.py
delpinos/crud/sqlalchemy/application/repositories/sqlalchemy_repository.py
delpinos/crud/sqlalchemy/configuration/functions.py
delpinos_crud_sqlalchemy-0.0.4.dist-info/METADATA
delpinos_crud_sqlalchemy-0.0.4.dist-info/WHEEL
delpinos_crud_sqlalchemy-0.0.4.dist-info/top_level.txt
delpinos_crud_sqlalchemy-0.0.4.dist-info/RECORD
