Metadata-Version: 2.1
Name: delpinos-crud-sqlalchemy
Version: 0.0.4
Summary: Delpinos Crud SqlAlchemy - Delpinos Framework
Author-email: Alef Bruno Delpino de Oliveira <alef@delpinos.com>
Keywords: delpinos,crud,sqlalchemy
Classifier: Programming Language :: Python :: 3
Classifier: Programming Language :: Python :: 3.10
Classifier: Topic :: Software Development :: Libraries :: Python Modules
Requires-Python: >=3.10
Requires-Dist: delpinos-core >=0.0.3
Requires-Dist: sqlalchemy-filters >=0.13.0
Requires-Dist: SQLAlchemy >=2.0.23
Requires-Dist: psycopg2-binary >=2.9.9
